llama_index/llms/friendli/__init__.py
llama_index/llms/friendli/base.py
llama_index/llms/friendli/utils.py
llama_index_llms_friendli-0.4.1.dist-info/METADATA
llama_index_llms_friendli-0.4.1.dist-info/WHEEL
llama_index_llms_friendli-0.4.1.dist-info/licenses/LICENSE
llama_index_llms_friendli-0.4.1.dist-info/RECORD
