Metadata-Version: 2.4
Name: llama-index-llms-friendli
Version: 0.4.1
Summary: llama-index llms friendli integration
Author-email: Yunmo Koo <yunmorning@friendli.ai>
License-Expression: MIT
License-File: LICENSE
Requires-Python: <4.0,>=3.9
Requires-Dist: friendli-client<2,>=1.2.4
Requires-Dist: llama-index-core<0.15,>=0.13.0
